Workbook

Sheet Inventario
A1: REFERENCIA | B1: DESCRIPCIÓN | C1: MARCA | D1: STOCK (piezas) | E1: Catálogo / pieza | F1: Total catálogo | G1: Facturado / pieza | H1: Costo IVA / pieza | I1: Fondo moto / pieza | J1: Costo real / pieza | K1: Precio mercado taller (opc.) | L1: Precio Taller / pieza | M1: Precio Público / pieza | N1: Ganancia Taller / pieza | O1: Ganancia Público / pieza | P1: Venta total Taller | Q1: Venta total Público | R1: Fondo Logística Acumulado | S1: Costo real total (stock) | T1: Ganancia total Taller | U1: Ganancia total Público | V1: Ahorro mayorista total (reinversión)
A2: KTR-4016 | B2: Terminal Dirección Optra DER | C2: Chevrolet | D2: 2 | E2: 27500 | F2: =D2*E2 | G2: 20625 | H2: 32725 | I2: 2618 | J2: 32725 | L2: 45300 | M2: 66300 | N2: 12575 | O2: 33575 | P2: 90600 | Q2: 132600 | R2: 5236 | S2: 65450 | T2: 25150 | U2: 67150 | V2: =ROUND((E2-G2)*D2,0)
A3: KSL-1005 | B3: Bieleta Estab. Luv Dmax 4x4 RT50 Del IZQ | C3: Chevrolet | D3: 2 | E3: 23630 | F3: =D3*E3 | G3: 17723 | H3: 28120 | I3: 2250 | J3: 28120 | L3: 38900 | M3: 56900 | N3: 10780 | O3: 28780 | P3: 77800 | Q3: 113800 | R3: 4500 | S3: 56240 | T3: 21560 | U3: 57560 | V3: =ROUND((E3-G3)*D3,0)
A4: KBJ-4013 | B4: Rótula Luv 2300 SUP | C4: Chevrolet | D4: 2 | E4: 31280 | F4: =D4*E4 | G4: 23460 | H4: 37223 | I4: 2978 | J4: 37223 | L4: 54900 | M4: 80400 | N4: 17677 | O4: 43177 | P4: 109800 | Q4: 160800 | R4: 5956 | S4: 74446 | T4: 35354 | U4: 86354 | V4: =ROUND((E4-G4)*D4,0)
A5: KTR-4035 | B5: Terminal Dirección Sail IZQ | C5: Chevrolet | D5: 2 | E5: 26580 | F5: =D5*E5 | G5: 19935 | H5: 31630 | I5: 2530 | J5: 31630 | L5: 43800 | M5: 64000 | N5: 12170 | O5: 32370 | P5: 87600 | Q5: 128000 | R5: 5060 | S5: 63260 | T5: 24340 | U5: 64740 | V5: =ROUND((E5-G5)*D5,0)
A6: KBJ-4001 | B6: Rótula Aveo-Sail | C6: Chevrolet | D6: 2 | E6: 23410 | F6: =D6*E6 | G6: 17558 | H6: 27858 | I6: 2229 | J6: 27858 | L6: 38500 | M6: 56400 | N6: 10642 | O6: 28542 | P6: 77000 | Q6: 112800 | R6: 4458 | S6: 55716 | T6: 21284 | U6: 57084 | V6: =ROUND((E6-G6)*D6,0)
A7: KTR-4034 | B7: Terminal Dirección Sail DER | C7: Chevrolet | D7: 2 | E7: 26580 | F7: =D7*E7 | G7: 19935 | H7: 31630 | I7: 2530 | J7: 31630 | L7: 43800 | M7: 64000 | N7: 12170 | O7: 32370 | P7: 87600 | Q7: 128000 | R7: 5060 | S7: 63260 | T7: 24340 | U7: 64740 | V7: =ROUND((E7-G7)*D7,0)
A8: KBJ-4008 | B8: Rótula Luv 2300 4x4 D-Max 4x2-4x4 Trooper INF (x2) | C8: Chevrolet | D8: 2 | E8: 47740 | F8: =D8*E8 | G8: 35805 | H8: 56811 | I8: 4545 | J8: 56811 | L8: 83900 | M8: 122700 | N8: 27089 | O8: 65889 | P8: 167800 | Q8: 245400 | R8: 9090 | S8: 113622 | T8: 54178 | U8: 131778 | V8: =ROUND((E8-G8)*D8,0)
A9: KTR-4019 | B9: Terminal Dir Spark GT 1.2 | C9: Chevrolet | D9: 2 | E9: 27680 | F9: =D9*E9 | G9: 20760 | H9: 32939 | I9: 2635 | J9: 32939 | L9: 45600 | M9: 66700 | N9: 12661 | O9: 33761 | P9: 91200 | Q9: 133400 | R9: 5270 | S9: 65878 | T9: 25322 | U9: 67522 | V9: =ROUND((E9-G9)*D9,0)
A10: KTR-4015 | B10: Terminal Dir Optra IZQ | C10: Chevrolet | D10: 2 | E10: 27500 | F10: =D10*E10 | G10: 20625 | H10: 32725 | I10: 2618 | J10: 32725 | L10: 45300 | M10: 66300 | N10: 12575 | O10: 33575 | P10: 90600 | Q10: 132600 | R10: 5236 | S10: 65450 | T10: 25150 | U10: 67150 | V10: =ROUND((E10-G10)*D10,0)
A11: KTR-4002 | B11: Terminal Dir Aveo DER | C11: Chevrolet | D11: 2 | E11: 24820 | F11: =D11*E11 | G11: 18615 | H11: 29536 | I11: 2363 | J11: 29536 | L11: 40900 | M11: 59800 | N11: 11364 | O11: 30264 | P11: 81800 | Q11: 119600 | R11: 4726 | S11: 59072 | T11: 22728 | U11: 60528 | V11: =ROUND((E11-G11)*D11,0)
A12: KTR-4003 | B12: Terminal Dir Aveo IZQ | C12: Chevrolet | D12: 2 | E12: 24820 | F12: =D12*E12 | G12: 18615 | H12: 29536 | I12: 2363 | J12: 29536 | L12: 40900 | M12: 59800 | N12: 11364 | O12: 30264 | P12: 81800 | Q12: 119600 | R12: 4726 | S12: 59072 | T12: 22728 | U12: 60528 | V12: =ROUND((E12-G12)*D12,0)
A13: KSL-1006 | B13: Bieleta Estab. Luv D-Max 4x4 RT-50 Del DER | C13: Chevrolet | D13: 2 | E13: 23630 | F13: =D13*E13 | G13: 17723 | H13: 28120 | I13: 2250 | J13: 28120 | L13: 38900 | M13: 56900 | N13: 10780 | O13: 28780 | P13: 77800 | Q13: 113800 | R13: 4500 | S13: 56240 | T13: 21560 | U13: 57560 | V13: =ROUND((E13-G13)*D13,0)
... A125: B32H-34-300 | B125: TIJERA DEL RH MAZDA 3 | C125: Mazda | D125: 1 | E125: 100840 | F125: =D125*E125 | G125: 90756 | H125: 120000 | I125: 9600 | J125: 120000 | L125: 189800 | M125: 277800 | N125: 69800 | O125: 157800 | P125: 189800 | Q125: 277800 | R125: 9600 | S125: 120000 | T125: 69800 | U125: 157800 | V125: =ROUND((E125-G125)*D125,0)
A126: ← NUEVO | D126: 0 | F126: =D126*E126 | P126: =D126*L126 | Q126: =D126*M126 | R126: =IF(I126>0,I126*D126,"") | S126: =IF(J126>0,J126*D126,"") | T126: =IF(S126>0,P126-S126,"") | U126: =IF(S126>0,Q126-S126,"") | V126: =ROUND((E126-G126)*D126,0)
D127: 0 | F127: =D127*E127 | P127: =D127*L127 | Q127: =D127*M127 | R127: =IF(I127>0,I127*D127,"") | S127: =IF(J127>0,J127*D127,"") | T127: =IF(S127>0,P127-S127,"") | U127: =IF(S127>0,Q127-S127,"") | V127: =ROUND((E127-G127)*D127,0)
D128: 0 | F128: =D128*E128 | P128: =D128*L128 | Q128: =D128*M128 | R128: =IF(I128>0,I128*D128,"") | S128: =IF(J128>0,J128*D128,"") | T128: =IF(S128>0,P128-S128,"") | U128: =IF(S128>0,Q128-S128,"") | V128: =ROUND((E128-G128)*D128,0)
D129: 0 | F129: =D129*E129 | P129: =D129*L129 | Q129: =D129*M129 | R129: =IF(I129>0,I129*D129,"") | S129: =IF(J129>0,J129*D129,"") | T129: =IF(S129>0,P129-S129,"") | U129: =IF(S129>0,Q129-S129,"") | V129: =ROUND((E129-G129)*D129,0)
D130: 0 | F130: =D130*E130 | P130: =D130*L130 | Q130: =D130*M130 | R130: =IF(I130>0,I130*D130,"") | S130: =IF(J130>0,J130*D130,"") | T130: =IF(S130>0,P130-S130,"") | U130: =IF(S130>0,Q130-S130,"") | V130: =ROUND((E130-G130)*D130,0)
D131: 0 | F131: =D131*E131 | P131: =D131*L131 | Q131: =D131*M131 | R131: =IF(I131>0,I131*D131,"") | S131: =IF(J131>0,J131*D131,"") | T131: =IF(S131>0,P131-S131,"") | U131: =IF(S131>0,Q131-S131,"") | V131: =ROUND((E131-G131)*D131,0)
D132: 0 | F132: =D132*E132 | P132: =D132*L132 | Q132: =D132*M132 | R132: =IF(I132>0,I132*D132,"") | S132: =IF(J132>0,J132*D132,"") | T132: =IF(S132>0,P132-S132,"") | U132: =IF(S132>0,Q132-S132,"") | V132: =ROUND((E132-G132)*D132,0)
D133: 0 | F133: =D133*E133 | P133: =D133*L133 | Q133: =D133*M133 | R133: =IF(I133>0,I133*D133,"") | S133: =IF(J133>0,J133*D133,"") | T133: =IF(S133>0,P133-S133,"") | U133: =IF(S133>0,Q133-S133,"") | V133: =ROUND((E133-G133)*D133,0)
D134: 0 | F134: =D134*E134 | P134: =D134*L134 | Q134: =D134*M134 | R134: =IF(I134>0,I134*D134,"") | S134: =IF(J134>0,J134*D134,"") | T134: =IF(S134>0,P134-S134,"") | U134: =IF(S134>0,Q134-S134,"") | V134: =ROUND((E134-G134)*D134,0)
D135: 0 | F135: =D135*E135 | P135: =D135*L135 | Q135: =D135*M135 | R135: =IF(I135>0,I135*D135,"") | S135: =IF(J135>0,J135*D135,"") | T135: =IF(S135>0,P135-S135,"") | U135: =IF(S135>0,Q135-S135,"") | V135: =ROUND((E135-G135)*D135,0)
D136: 0 | F136: =D136*E136 | P136: =D136*L136 | Q136: =D136*M136 | R136: =IF(I136>0,I136*D136,"") | S136: =IF(J136>0,J136*D136,"") | T136: =IF(S136>0,P136-S136,"") | U136: =IF(S136>0,Q136-S136,"") | V136: =ROUND((E136-G136)*D136,0)
D137: 0 | F137: =D137*E137 | P137: =D137*L137 | Q137: =D137*M137 | R137: =IF(I137>0,I137*D137,"") | S137: =IF(J137>0,J137*D137,"") | T137: =IF(S137>0,P137-S137,"") | U137: =IF(S137>0,Q137-S137,"") | V137: =ROUND((E137-G137)*D137,0)
D138: 0 | F138: =D138*E138 | P138: =D138*L138 | Q138: =D138*M138 | R138: =IF(I138>0,I138*D138,"") | S138: =IF(J138>0,J138*D138,"") | T138: =IF(S138>0,P138-S138,"") | U138: =IF(S138>0,Q138-S138,"") | V138: =ROUND((E138-G138)*D138,0)
... D155: 0 | F155: =D155*E155 | P155: =D155*L155 | Q155: =D155*M155 | R155: =IF(I155>0,I155*D155,"") | S155: =IF(J155>0,J155*D155,"") | T155: =IF(S155>0,P155-S155,"") | U155: =IF(S155>0,Q155-S155,"") | V155: =ROUND((E155-G155)*D155,0)

Sheet Movimientos
A1: Fecha | B1: Hora | C1: Referencia | D1: Tipo | E1: Cantidad | F1: Stock anterior | G1: Stock nuevo | H1: Motivo | I1: Usuario
A2: 2026-06-08 | B2: 19:29 | C2: (TODAS) | D2: Compra | E2: 220 | F2: 0 | G2: 220 | H2: Carga inicial pedido 5 Junio | I2: sistema
A3: 2026-06-08 | B3: 19:31 | C3: KTR-4015 | D3: Venta | E3: -1 | F3: 2 | G3: 1 | H3: Prueba venta | I3: operador
A4: 2026-06-08 | B4: 19:31 | C4: KTR-4015 | D4: Sincronización | E4: -1 | F4: 2 | G4: 1 | H4: Ajuste detectado al sincronizar (cambio en Excel) | I4: sistema
A5: 2026-06-08 | B5: 19:36 | C5: KTR-4015 | D5: Venta | E5: -1 | F5: 1 | G5: 0 | H5: Prueba | I5: operador
A6: 2026-06-08 | B6: 19:43 | C6: KTR-4015 | D6: Entrada | E6: 2 | F6: 0 | G6: 2 | H6: Restaurar stock inicial | I6: operador

Sheet Guía producto nuevo
A1: Paso | B1: Instrucción
A2: 1. Cambiar stock | B2: Edita columna amarilla STOCK (piezas) en hoja Inventario.
A3: 2. Registrar movimiento | B3: Ejecuta: py -3 registrar_movimiento.py REF -1 "Venta taller"
A4: 3. Sincronizar PWA | B4: Ejecuta: py -3 sincronizar_inventario.py
A5: 4. Agregar producto nuevo | B5: En Inventario, busca fila ← NUEVO. Llena REFERENCIA, DESCRIPCIÓN, MARCA, STOCK, Catálogo y Facturado. Los precios Taller/Público se pueden calcular con el script o pegar manualmente.
A6: 5. Calcular precios auto | B6: py -3 inventario.py precios REFERENCIA — calcula taller/público desde catálogo.
A7: 6. Ocultar columnas grises | B7: Selecciona P–S → clic derecho → Ocultar.
A8: 7. Desbloquear edición | B8: Si Excel pide contraseña de hoja: apex
A9: 8. Plantilla vacía | B9: Usa Inventario_Apex_PLANTILLA.xlsx para empezar desde cero.
A10: 9. Pedido histórico | B10: Los análisis de pedidos van en carpeta pedidos/ — no mezclar con el VIVO.

Sheet Alertas
A1: Prioridad | B1: REFERENCIA | C1: DESCRIPCIÓN | D1: STOCK | E1: Acción sugerida
A2: STOCK BAJO | B2: KSA-CH043 | C2: Amortiguador Captiva 18-08 2.4 Del IZQ | D2: 1 | E2: Revisar / reponer pronto
A3: STOCK BAJO | B3: KSA-CH042 | C3: Amortiguador Captiva 18-08 2.4 Del DER | D3: 1 | E3: Revisar / reponer pronto
A4: STOCK BAJO | B4: KSA-DA001 | C4: Amortiguador Spark 7.24 / Daewoo Matiz II Del DER | D4: 1 | E4: Revisar / reponer pronto
A5: STOCK BAJO | B5: KSA-DA002 | C5: Amortiguador Spark 7.24 / Daewoo Matiz II Del IZQ | D5: 1 | E5: Revisar / reponer pronto
A6: STOCK BAJO | B6: KSA-FO001 | C6: Amortiguador Ford Fiesta Del IZQ | D6: 1 | E6: Revisar / reponer pronto
A7: STOCK BAJO | B7: KSA-FO002 | C7: Amortiguador Ford Fiesta Del DER | D7: 1 | E7: Revisar / reponer pronto
A8: STOCK BAJO | B8: KSA-HY014 | C8: Amortiguador Accent Vision / Kia Rio Xcite DEL DER | D8: 1 | E8: Revisar / reponer pronto
A9: STOCK BAJO | B9: KSA-HY015 | C9: Amortiguador Accent Vision / Kia Rio Xcite DEL IZQ | D9: 1 | E9: Revisar / reponer pronto
A10: STOCK BAJO | B10: KSA-KI024 | C10: Amortiguador Picanto ION Delantero Der GAS | D10: 1 | E10: Revisar / reponer pronto
A11: STOCK BAJO | B11: KSA-KI025 | C11: Amortiguador Kia Picanto 17-13 ION Del IZQ GAS | D11: 1 | E11: Revisar / reponer pronto
A12: STOCK BAJO | B12: KSA-MA001 | C12: Amortiguador Mazda 2 13-08 Del DER GAS | D12: 1 | E12: Revisar / reponer pronto
A13: STOCK BAJO | B13: KSA-MA002 | C13: Amortiguador Mazda 2 13-08 Del IZQ GAS | D13: 1 | E13: Revisar / reponer pronto
... A29: STOCK BAJO | B29: B32H-34-300 | C29: TIJERA DEL RH MAZDA 3 | D29: 1 | E29: Revisar / reponer pronto

Sheet Resumen
A1: Concepto | B1: Valor
A2: Total referencias activas | B2: =COUNTIF('Inventario'!A2:A155,"?*")
A3: Total piezas en stock | B3: =SUM('Inventario'!D2:D155)
A5: ── INVERSIÓN ──
A6: Inversión facturas con IVA (stock) | B6: =SUMPRODUCT('Inventario'!H2:H155,'Inventario'!D2:D155)
A7: Costo real total en bodega | B7: =SUM('Inventario'!S2:S155)
A8: Fondo logística moto (stock) | B8: =SUM('Inventario'!R2:R155)
A10: ── GANANCIA SI VENDES TODO EL STOCK ──
A11: Ganancia total Taller | B11: =SUM('Inventario'!T2:T155)
A12: Ganancia total Público | B12: =SUM('Inventario'!U2:U155)
A14: ── OTROS ──
A15: Ahorro mayorista (reinversión) | B15: =SUM('Inventario'!V2:V155)
A16: Última actualización precios | B16: 2026-06-23 16:23
