Workbook

Sheet Inventario
A1: REFERENCIA | B1: DESCRIPCIÓN | C1: MARCA | D1: STOCK (piezas) | E1: Catálogo / pieza | F1: Total catálogo | G1: Facturado / pieza | H1: Total pagado factura (IVA) | I1: Precio Taller / pieza | J1: Precio Público / pieza | K1: Venta total Taller | L1: Venta total Público | M1: Costo real total | N1: Ganancia total Taller | O1: Ganancia total Público | P1: Ahorro mayorista total (reinversión) | Q1: Fondo logística total ($10k/pza) | R1: Ganancia neta Taller (sin domicilio) | S1: Ganancia neta Público (sin domicilio)
A2: ← NUEVO | D2: 0 | F2: =D2*E2 | H2: =ROUND(D2*G2*1.19,0) | K2: =D2*I2 | L2: =D2*J2 | M2: =H2+Q2 | N2: =K2-M2 | O2: =L2-M2 | P2: =ROUND((E2-G2)*D2,0) | Q2: =D2*10000 | R2: =K2-H2 | S2: =L2-H2
D3: 0 | F3: =D3*E3 | H3: =ROUND(D3*G3*1.19,0) | K3: =D3*I3 | L3: =D3*J3 | M3: =H3+Q3 | N3: =K3-M3 | O3: =L3-M3 | P3: =ROUND((E3-G3)*D3,0) | Q3: =D3*10000 | R3: =K3-H3 | S3: =L3-H3
D4: 0 | F4: =D4*E4 | H4: =ROUND(D4*G4*1.19,0) | K4: =D4*I4 | L4: =D4*J4 | M4: =H4+Q4 | N4: =K4-M4 | O4: =L4-M4 | P4: =ROUND((E4-G4)*D4,0) | Q4: =D4*10000 | R4: =K4-H4 | S4: =L4-H4
D5: 0 | F5: =D5*E5 | H5: =ROUND(D5*G5*1.19,0) | K5: =D5*I5 | L5: =D5*J5 | M5: =H5+Q5 | N5: =K5-M5 | O5: =L5-M5 | P5: =ROUND((E5-G5)*D5,0) | Q5: =D5*10000 | R5: =K5-H5 | S5: =L5-H5
D6: 0 | F6: =D6*E6 | H6: =ROUND(D6*G6*1.19,0) | K6: =D6*I6 | L6: =D6*J6 | M6: =H6+Q6 | N6: =K6-M6 | O6: =L6-M6 | P6: =ROUND((E6-G6)*D6,0) | Q6: =D6*10000 | R6: =K6-H6 | S6: =L6-H6
D7: 0 | F7: =D7*E7 | H7: =ROUND(D7*G7*1.19,0) | K7: =D7*I7 | L7: =D7*J7 | M7: =H7+Q7 | N7: =K7-M7 | O7: =L7-M7 | P7: =ROUND((E7-G7)*D7,0) | Q7: =D7*10000 | R7: =K7-H7 | S7: =L7-H7
D8: 0 | F8: =D8*E8 | H8: =ROUND(D8*G8*1.19,0) | K8: =D8*I8 | L8: =D8*J8 | M8: =H8+Q8 | N8: =K8-M8 | O8: =L8-M8 | P8: =ROUND((E8-G8)*D8,0) | Q8: =D8*10000 | R8: =K8-H8 | S8: =L8-H8
D9: 0 | F9: =D9*E9 | H9: =ROUND(D9*G9*1.19,0) | K9: =D9*I9 | L9: =D9*J9 | M9: =H9+Q9 | N9: =K9-M9 | O9: =L9-M9 | P9: =ROUND((E9-G9)*D9,0) | Q9: =D9*10000 | R9: =K9-H9 | S9: =L9-H9
D10: 0 | F10: =D10*E10 | H10: =ROUND(D10*G10*1.19,0) | K10: =D10*I10 | L10: =D10*J10 | M10: =H10+Q10 | N10: =K10-M10 | O10: =L10-M10 | P10: =ROUND((E10-G10)*D10,0) | Q10: =D10*10000 | R10: =K10-H10 | S10: =L10-H10
D11: 0 | F11: =D11*E11 | H11: =ROUND(D11*G11*1.19,0) | K11: =D11*I11 | L11: =D11*J11 | M11: =H11+Q11 | N11: =K11-M11 | O11: =L11-M11 | P11: =ROUND((E11-G11)*D11,0) | Q11: =D11*10000 | R11: =K11-H11 | S11: =L11-H11
D12: 0 | F12: =D12*E12 | H12: =ROUND(D12*G12*1.19,0) | K12: =D12*I12 | L12: =D12*J12 | M12: =H12+Q12 | N12: =K12-M12 | O12: =L12-M12 | P12: =ROUND((E12-G12)*D12,0) | Q12: =D12*10000 | R12: =K12-H12 | S12: =L12-H12
D13: 0 | F13: =D13*E13 | H13: =ROUND(D13*G13*1.19,0) | K13: =D13*I13 | L13: =D13*J13 | M13: =H13+Q13 | N13: =K13-M13 | O13: =L13-M13 | P13: =ROUND((E13-G13)*D13,0) | Q13: =D13*10000 | R13: =K13-H13 | S13: =L13-H13
D14: 0 | F14: =D14*E14 | H14: =ROUND(D14*G14*1.19,0) | K14: =D14*I14 | L14: =D14*J14 | M14: =H14+Q14 | N14: =K14-M14 | O14: =L14-M14 | P14: =ROUND((E14-G14)*D14,0) | Q14: =D14*10000 | R14: =K14-H14 | S14: =L14-H14
... D31: 0 | F31: =D31*E31 | H31: =ROUND(D31*G31*1.19,0) | K31: =D31*I31 | L31: =D31*J31 | M31: =H31+Q31 | N31: =K31-M31 | O31: =L31-M31 | P31: =ROUND((E31-G31)*D31,0) | Q31: =D31*10000 | R31: =K31-H31 | S31: =L31-H31

Sheet Movimientos
A1: Fecha | B1: Hora | C1: Referencia | D1: Tipo | E1: Cantidad | F1: Stock anterior | G1: Stock nuevo | H1: Motivo | I1: Usuario

Sheet Alertas
A1: Prioridad | B1: REFERENCIA | C1: DESCRIPCIÓN | D1: STOCK | E1: Acción sugerida
A2: OK | B2: Sin alertas | E2: Todo el stock está por encima de 1 pieza

Sheet Resumen
A1: Concepto | B1: Valor
A2: Total referencias activas | B2: =COUNTIF('Inventario'!A2:A31,"?*")
A3: Total piezas en stock | B3: =SUM('Inventario'!D2:D31)
A4: Alertas stock bajo (≤1) | B4: =COUNTIF('Inventario'!D2:D31,"<=1")
A6: ── INVERSIÓN ──
A7: Inversión en facturas (con IVA) | B7: =SUM('Inventario'!H2:H31)
A9: ── GANANCIA NETA REAL ──
A10: ★ Ganancia neta Taller | B10: =SUM('Inventario'!R2:R31)
A11: ★ Ganancia neta Público | B11: =SUM('Inventario'!S2:S31)
A12: ↳ Inversión YA descontada. NO restar otra vez.
A14: ── OPERATIVO ──
A15: Ganancia operativa Taller | B15: =SUM('Inventario'!N2:N31)
A16: Fondo logística domicilios | B16: =SUM('Inventario'!Q2:Q31)
A17: Ahorro mayorista (reinversión) | B17: =SUM('Inventario'!P2:P31)
A18: Última sincronización PWA | B18: 2026-06-08 19:29

Sheet Guía producto nuevo
A1: Paso | B1: Instrucción
A2: 1. Cambiar stock | B2: Edita columna amarilla STOCK (piezas) en hoja Inventario.
A3: 2. Registrar movimiento | B3: Ejecuta: py -3 registrar_movimiento.py REF -1 "Venta taller"
A4: 3. Sincronizar PWA | B4: Ejecuta: py -3 sincronizar_inventario.py
A5: 4. Agregar producto nuevo | B5: En Inventario, busca fila ← NUEVO. Llena REFERENCIA, DESCRIPCIÓN, MARCA, STOCK, Catálogo y Facturado. Los precios Taller/Público se pueden calcular con el script o pegar manualmente.
A6: 5. Calcular precios auto | B6: py -3 inventario.py precios REFERENCIA — calcula taller/público desde catálogo.
A7: 6. Ocultar columnas grises | B7: Selecciona P–S → clic derecho → Ocultar.
A8: 7. Desbloquear edición | B8: Si Excel pide contraseña de hoja: apex
A9: 8. Plantilla vacía | B9: Usa Inventario_Apex_PLANTILLA.xlsx para empezar desde cero.
A10: 9. Pedido histórico | B10: Los análisis de pedidos van en carpeta pedidos/ — no mezclar con el VIVO.
