Workbook

Sheet Inventario
A1: REFERENCIA | B1: DESCRIPCIÓN | C1: MARCA | D1: STOCK (piezas) | E1: Catálogo / pieza | F1: Total catálogo | G1: Facturado / pieza | H1: Costo IVA / pieza | I1: Fondo moto / pieza | J1: Costo real / pieza | K1: Precio Taller / pieza | L1: Precio Público / pieza | M1: Ganancia Taller / pieza | N1: Ganancia Público / pieza | O1: Venta total Taller | P1: Venta total Público | Q1: Fondo Logística Acumulado | R1: Costo real total (stock) | S1: Ganancia total Taller | T1: Ganancia total Público | U1: Ahorro mayorista total (reinversión)
A2: KTR-4016 | B2: Terminal Dirección Optra DER | C2: Chevrolet | D2: 2 | E2: 27500 | F2: =D2*E2 | G2: 20625 | H2: =IF(G2>0,ROUND(G2*1.19,0),"") | I2: =IF(H2>0,ROUND(H2*0.08,0),"") | J2: =IF(H2>0,H2+I2,"") | K2: 40800 | L2: 48200 | M2: =IF(AND(K2>0,J2>0),K2-J2,"") | N2: =IF(AND(L2>0,J2>0),L2-J2,"") | O2: =D2*K2 | P2: =D2*L2 | Q2: =IF(I2>0,I2*D2,"") | R2: =IF(J2>0,J2*D2,"") | S2: =IF(R2>0,O2-R2,"") | T2: =IF(R2>0,P2-R2,"") | U2: =ROUND((E2-G2)*D2,0)
A3: KSL-1005 | B3: Bieleta Estab. Luv Dmax 4x4 RT50 Del IZQ | C3: Chevrolet | D3: 2 | E3: 23630 | F3: =D3*E3 | G3: 17723 | H3: =IF(G3>0,ROUND(G3*1.19,0),"") | I3: =IF(H3>0,ROUND(H3*0.08,0),"") | J3: =IF(H3>0,H3+I3,"") | K3: 35000 | L3: 41400 | M3: =IF(AND(K3>0,J3>0),K3-J3,"") | N3: =IF(AND(L3>0,J3>0),L3-J3,"") | O3: =D3*K3 | P3: =D3*L3 | Q3: =IF(I3>0,I3*D3,"") | R3: =IF(J3>0,J3*D3,"") | S3: =IF(R3>0,O3-R3,"") | T3: =IF(R3>0,P3-R3,"") | U3: =ROUND((E3-G3)*D3,0)
A4: KBJ-4013 | B4: Rótula Luv 2300 SUP | C4: Chevrolet | D4: 2 | E4: 31280 | F4: =D4*E4 | G4: 23460 | H4: =IF(G4>0,ROUND(G4*1.19,0),"") | I4: =IF(H4>0,ROUND(H4*0.08,0),"") | J4: =IF(H4>0,H4+I4,"") | K4: 46400 | L4: 54800 | M4: =IF(AND(K4>0,J4>0),K4-J4,"") | N4: =IF(AND(L4>0,J4>0),L4-J4,"") | O4: =D4*K4 | P4: =D4*L4 | Q4: =IF(I4>0,I4*D4,"") | R4: =IF(J4>0,J4*D4,"") | S4: =IF(R4>0,O4-R4,"") | T4: =IF(R4>0,P4-R4,"") | U4: =ROUND((E4-G4)*D4,0)
A5: KTR-4035 | B5: Terminal Dirección Sail IZQ | C5: Chevrolet | D5: 2 | E5: 26580 | F5: =D5*E5 | G5: 19935 | H5: =IF(G5>0,ROUND(G5*1.19,0),"") | I5: =IF(H5>0,ROUND(H5*0.08,0),"") | J5: =IF(H5>0,H5+I5,"") | K5: 39400 | L5: 46600 | M5: =IF(AND(K5>0,J5>0),K5-J5,"") | N5: =IF(AND(L5>0,J5>0),L5-J5,"") | O5: =D5*K5 | P5: =D5*L5 | Q5: =IF(I5>0,I5*D5,"") | R5: =IF(J5>0,J5*D5,"") | S5: =IF(R5>0,O5-R5,"") | T5: =IF(R5>0,P5-R5,"") | U5: =ROUND((E5-G5)*D5,0)
A6: KBJ-4001 | B6: Rótula Aveo-Sail | C6: Chevrolet | D6: 2 | E6: 23410 | F6: =D6*E6 | G6: 17558 | H6: =IF(G6>0,ROUND(G6*1.19,0),"") | I6: =IF(H6>0,ROUND(H6*0.08,0),"") | J6: =IF(H6>0,H6+I6,"") | K6: 34700 | L6: 41000 | M6: =IF(AND(K6>0,J6>0),K6-J6,"") | N6: =IF(AND(L6>0,J6>0),L6-J6,"") | O6: =D6*K6 | P6: =D6*L6 | Q6: =IF(I6>0,I6*D6,"") | R6: =IF(J6>0,J6*D6,"") | S6: =IF(R6>0,O6-R6,"") | T6: =IF(R6>0,P6-R6,"") | U6: =ROUND((E6-G6)*D6,0)
A7: KTR-4034 | B7: Terminal Dirección Sail DER | C7: Chevrolet | D7: 2 | E7: 26580 | F7: =D7*E7 | G7: 19935 | H7: =IF(G7>0,ROUND(G7*1.19,0),"") | I7: =IF(H7>0,ROUND(H7*0.08,0),"") | J7: =IF(H7>0,H7+I7,"") | K7: 39400 | L7: 46600 | M7: =IF(AND(K7>0,J7>0),K7-J7,"") | N7: =IF(AND(L7>0,J7>0),L7-J7,"") | O7: =D7*K7 | P7: =D7*L7 | Q7: =IF(I7>0,I7*D7,"") | R7: =IF(J7>0,J7*D7,"") | S7: =IF(R7>0,O7-R7,"") | T7: =IF(R7>0,P7-R7,"") | U7: =ROUND((E7-G7)*D7,0)
A8: KBJ-4008 | B8: Rótula Luv 2300 4x4 D-Max 4x2-4x4 Trooper INF (x2) | C8: Chevrolet | D8: 2 | E8: 47740 | F8: =D8*E8 | G8: 35805 | H8: =IF(G8>0,ROUND(G8*1.19,0),"") | I8: =IF(H8>0,ROUND(H8*0.08,0),"") | J8: =IF(H8>0,H8+I8,"") | K8: 61400 | L8: 70800 | M8: =IF(AND(K8>0,J8>0),K8-J8,"") | N8: =IF(AND(L8>0,J8>0),L8-J8,"") | O8: =D8*K8 | P8: =D8*L8 | Q8: =IF(I8>0,I8*D8,"") | R8: =IF(J8>0,J8*D8,"") | S8: =IF(R8>0,O8-R8,"") | T8: =IF(R8>0,P8-R8,"") | U8: =ROUND((E8-G8)*D8,0)
A9: KTR-4019 | B9: Terminal Dir Spark GT 1.2 | C9: Chevrolet | D9: 2 | E9: 27680 | F9: =D9*E9 | G9: 20760 | H9: =IF(G9>0,ROUND(G9*1.19,0),"") | I9: =IF(H9>0,ROUND(H9*0.08,0),"") | J9: =IF(H9>0,H9+I9,"") | K9: 41000 | L9: 48500 | M9: =IF(AND(K9>0,J9>0),K9-J9,"") | N9: =IF(AND(L9>0,J9>0),L9-J9,"") | O9: =D9*K9 | P9: =D9*L9 | Q9: =IF(I9>0,I9*D9,"") | R9: =IF(J9>0,J9*D9,"") | S9: =IF(R9>0,O9-R9,"") | T9: =IF(R9>0,P9-R9,"") | U9: =ROUND((E9-G9)*D9,0)
A10: KTR-4015 | B10: Terminal Dir Optra IZQ | C10: Chevrolet | D10: 2 | E10: 27500 | F10: =D10*E10 | G10: 20625 | H10: =IF(G10>0,ROUND(G10*1.19,0),"") | I10: =IF(H10>0,ROUND(H10*0.08,0),"") | J10: =IF(H10>0,H10+I10,"") | K10: 40800 | L10: 48200 | M10: =IF(AND(K10>0,J10>0),K10-J10,"") | N10: =IF(AND(L10>0,J10>0),L10-J10,"") | O10: =D10*K10 | P10: =D10*L10 | Q10: =IF(I10>0,I10*D10,"") | R10: =IF(J10>0,J10*D10,"") | S10: =IF(R10>0,O10-R10,"") | T10: =IF(R10>0,P10-R10,"") | U10: =ROUND((E10-G10)*D10,0)
A11: KTR-4002 | B11: Terminal Dir Aveo DER | C11: Chevrolet | D11: 2 | E11: 24820 | F11: =D11*E11 | G11: 18615 | H11: =IF(G11>0,ROUND(G11*1.19,0),"") | I11: =IF(H11>0,ROUND(H11*0.08,0),"") | J11: =IF(H11>0,H11+I11,"") | K11: 36800 | L11: 43500 | M11: =IF(AND(K11>0,J11>0),K11-J11,"") | N11: =IF(AND(L11>0,J11>0),L11-J11,"") | O11: =D11*K11 | P11: =D11*L11 | Q11: =IF(I11>0,I11*D11,"") | R11: =IF(J11>0,J11*D11,"") | S11: =IF(R11>0,O11-R11,"") | T11: =IF(R11>0,P11-R11,"") | U11: =ROUND((E11-G11)*D11,0)
A12: KTR-4003 | B12: Terminal Dir Aveo IZQ | C12: Chevrolet | D12: 2 | E12: 24820 | F12: =D12*E12 | G12: 18615 | H12: =IF(G12>0,ROUND(G12*1.19,0),"") | I12: =IF(H12>0,ROUND(H12*0.08,0),"") | J12: =IF(H12>0,H12+I12,"") | K12: 36800 | L12: 43500 | M12: =IF(AND(K12>0,J12>0),K12-J12,"") | N12: =IF(AND(L12>0,J12>0),L12-J12,"") | O12: =D12*K12 | P12: =D12*L12 | Q12: =IF(I12>0,I12*D12,"") | R12: =IF(J12>0,J12*D12,"") | S12: =IF(R12>0,O12-R12,"") | T12: =IF(R12>0,P12-R12,"") | U12: =ROUND((E12-G12)*D12,0)
A13: KSL-1006 | B13: Bieleta Estab. Luv D-Max 4x4 RT-50 Del DER | C13: Chevrolet | D13: 2 | E13: 23630 | F13: =D13*E13 | G13: 17723 | H13: =IF(G13>0,ROUND(G13*1.19,0),"") | I13: =IF(H13>0,ROUND(H13*0.08,0),"") | J13: =IF(H13>0,H13+I13,"") | K13: 35000 | L13: 41400 | M13: =IF(AND(K13>0,J13>0),K13-J13,"") | N13: =IF(AND(L13>0,J13>0),L13-J13,"") | O13: =D13*K13 | P13: =D13*L13 | Q13: =IF(I13>0,I13*D13,"") | R13: =IF(J13>0,J13*D13,"") | S13: =IF(R13>0,O13-R13,"") | T13: =IF(R13>0,P13-R13,"") | U13: =ROUND((E13-G13)*D13,0)
... A125: B32H-34-300 | B125: TIJERA DEL RH MAZDA 3 | C125: Mazda | D125: 1 | E125: 100840 | F125: =D125*E125 | G125: 90756 | H125: =IF(G125>0,ROUND(G125*1.19,0),"") | I125: =IF(H125>0,ROUND(H125*0.08,0),"") | J125: =IF(H125>0,H125+I125,"") | K125: 137200 | L125: 155500 | M125: =IF(AND(K125>0,J125>0),K125-J125,"") | N125: =IF(AND(L125>0,J125>0),L125-J125,"") | O125: =D125*K125 | P125: =D125*L125 | Q125: =IF(I125>0,I125*D125,"") | R125: =IF(J125>0,J125*D125,"") | S125: =IF(R125>0,O125-R125,"") | T125: =IF(R125>0,P125-R125,"") | U125: =ROUND((E125-G125)*D125,0)
A126: ← NUEVO | D126: 0 | F126: =D126*E126 | H126: =IF(G126>0,ROUND(G126*1.19,0),"") | I126: =IF(H126>0,ROUND(H126*0.08,0),"") | J126: =IF(H126>0,H126+I126,"") | M126: =IF(AND(K126>0,J126>0),K126-J126,"") | N126: =IF(AND(L126>0,J126>0),L126-J126,"") | O126: =D126*K126 | P126: =D126*L126 | Q126: =IF(I126>0,I126*D126,"") | R126: =IF(J126>0,J126*D126,"") | S126: =IF(R126>0,O126-R126,"") | T126: =IF(R126>0,P126-R126,"") | U126: =ROUND((E126-G126)*D126,0)
A127: nan | D127: 0 | F127: =D127*E127 | H127: =IF(G127>0,ROUND(G127*1.19,0),"") | I127: =IF(H127>0,ROUND(H127*0.08,0),"") | J127: =IF(H127>0,H127+I127,"") | M127: =IF(AND(K127>0,J127>0),K127-J127,"") | N127: =IF(AND(L127>0,J127>0),L127-J127,"") | O127: =D127*K127 | P127: =D127*L127 | Q127: =IF(I127>0,I127*D127,"") | R127: =IF(J127>0,J127*D127,"") | S127: =IF(R127>0,O127-R127,"") | T127: =IF(R127>0,P127-R127,"") | U127: =ROUND((E127-G127)*D127,0)
A128: nan | D128: 0 | F128: =D128*E128 | H128: =IF(G128>0,ROUND(G128*1.19,0),"") | I128: =IF(H128>0,ROUND(H128*0.08,0),"") | J128: =IF(H128>0,H128+I128,"") | M128: =IF(AND(K128>0,J128>0),K128-J128,"") | N128: =IF(AND(L128>0,J128>0),L128-J128,"") | O128: =D128*K128 | P128: =D128*L128 | Q128: =IF(I128>0,I128*D128,"") | R128: =IF(J128>0,J128*D128,"") | S128: =IF(R128>0,O128-R128,"") | T128: =IF(R128>0,P128-R128,"") | U128: =ROUND((E128-G128)*D128,0)
A129: nan | D129: 0 | F129: =D129*E129 | H129: =IF(G129>0,ROUND(G129*1.19,0),"") | I129: =IF(H129>0,ROUND(H129*0.08,0),"") | J129: =IF(H129>0,H129+I129,"") | M129: =IF(AND(K129>0,J129>0),K129-J129,"") | N129: =IF(AND(L129>0,J129>0),L129-J129,"") | O129: =D129*K129 | P129: =D129*L129 | Q129: =IF(I129>0,I129*D129,"") | R129: =IF(J129>0,J129*D129,"") | S129: =IF(R129>0,O129-R129,"") | T129: =IF(R129>0,P129-R129,"") | U129: =ROUND((E129-G129)*D129,0)
A130: nan | D130: 0 | F130: =D130*E130 | H130: =IF(G130>0,ROUND(G130*1.19,0),"") | I130: =IF(H130>0,ROUND(H130*0.08,0),"") | J130: =IF(H130>0,H130+I130,"") | M130: =IF(AND(K130>0,J130>0),K130-J130,"") | N130: =IF(AND(L130>0,J130>0),L130-J130,"") | O130: =D130*K130 | P130: =D130*L130 | Q130: =IF(I130>0,I130*D130,"") | R130: =IF(J130>0,J130*D130,"") | S130: =IF(R130>0,O130-R130,"") | T130: =IF(R130>0,P130-R130,"") | U130: =ROUND((E130-G130)*D130,0)
A131: nan | D131: 0 | F131: =D131*E131 | H131: =IF(G131>0,ROUND(G131*1.19,0),"") | I131: =IF(H131>0,ROUND(H131*0.08,0),"") | J131: =IF(H131>0,H131+I131,"") | M131: =IF(AND(K131>0,J131>0),K131-J131,"") | N131: =IF(AND(L131>0,J131>0),L131-J131,"") | O131: =D131*K131 | P131: =D131*L131 | Q131: =IF(I131>0,I131*D131,"") | R131: =IF(J131>0,J131*D131,"") | S131: =IF(R131>0,O131-R131,"") | T131: =IF(R131>0,P131-R131,"") | U131: =ROUND((E131-G131)*D131,0)
A132: nan | D132: 0 | F132: =D132*E132 | H132: =IF(G132>0,ROUND(G132*1.19,0),"") | I132: =IF(H132>0,ROUND(H132*0.08,0),"") | J132: =IF(H132>0,H132+I132,"") | M132: =IF(AND(K132>0,J132>0),K132-J132,"") | N132: =IF(AND(L132>0,J132>0),L132-J132,"") | O132: =D132*K132 | P132: =D132*L132 | Q132: =IF(I132>0,I132*D132,"") | R132: =IF(J132>0,J132*D132,"") | S132: =IF(R132>0,O132-R132,"") | T132: =IF(R132>0,P132-R132,"") | U132: =ROUND((E132-G132)*D132,0)
A133: nan | D133: 0 | F133: =D133*E133 | H133: =IF(G133>0,ROUND(G133*1.19,0),"") | I133: =IF(H133>0,ROUND(H133*0.08,0),"") | J133: =IF(H133>0,H133+I133,"") | M133: =IF(AND(K133>0,J133>0),K133-J133,"") | N133: =IF(AND(L133>0,J133>0),L133-J133,"") | O133: =D133*K133 | P133: =D133*L133 | Q133: =IF(I133>0,I133*D133,"") | R133: =IF(J133>0,J133*D133,"") | S133: =IF(R133>0,O133-R133,"") | T133: =IF(R133>0,P133-R133,"") | U133: =ROUND((E133-G133)*D133,0)
A134: nan | D134: 0 | F134: =D134*E134 | H134: =IF(G134>0,ROUND(G134*1.19,0),"") | I134: =IF(H134>0,ROUND(H134*0.08,0),"") | J134: =IF(H134>0,H134+I134,"") | M134: =IF(AND(K134>0,J134>0),K134-J134,"") | N134: =IF(AND(L134>0,J134>0),L134-J134,"") | O134: =D134*K134 | P134: =D134*L134 | Q134: =IF(I134>0,I134*D134,"") | R134: =IF(J134>0,J134*D134,"") | S134: =IF(R134>0,O134-R134,"") | T134: =IF(R134>0,P134-R134,"") | U134: =ROUND((E134-G134)*D134,0)
A135: nan | D135: 0 | F135: =D135*E135 | H135: =IF(G135>0,ROUND(G135*1.19,0),"") | I135: =IF(H135>0,ROUND(H135*0.08,0),"") | J135: =IF(H135>0,H135+I135,"") | M135: =IF(AND(K135>0,J135>0),K135-J135,"") | N135: =IF(AND(L135>0,J135>0),L135-J135,"") | O135: =D135*K135 | P135: =D135*L135 | Q135: =IF(I135>0,I135*D135,"") | R135: =IF(J135>0,J135*D135,"") | S135: =IF(R135>0,O135-R135,"") | T135: =IF(R135>0,P135-R135,"") | U135: =ROUND((E135-G135)*D135,0)
A136: nan | D136: 0 | F136: =D136*E136 | H136: =IF(G136>0,ROUND(G136*1.19,0),"") | I136: =IF(H136>0,ROUND(H136*0.08,0),"") | J136: =IF(H136>0,H136+I136,"") | M136: =IF(AND(K136>0,J136>0),K136-J136,"") | N136: =IF(AND(L136>0,J136>0),L136-J136,"") | O136: =D136*K136 | P136: =D136*L136 | Q136: =IF(I136>0,I136*D136,"") | R136: =IF(J136>0,J136*D136,"") | S136: =IF(R136>0,O136-R136,"") | T136: =IF(R136>0,P136-R136,"") | U136: =ROUND((E136-G136)*D136,0)
A137: nan | D137: 0 | F137: =D137*E137 | H137: =IF(G137>0,ROUND(G137*1.19,0),"") | I137: =IF(H137>0,ROUND(H137*0.08,0),"") | J137: =IF(H137>0,H137+I137,"") | M137: =IF(AND(K137>0,J137>0),K137-J137,"") | N137: =IF(AND(L137>0,J137>0),L137-J137,"") | O137: =D137*K137 | P137: =D137*L137 | Q137: =IF(I137>0,I137*D137,"") | R137: =IF(J137>0,J137*D137,"") | S137: =IF(R137>0,O137-R137,"") | T137: =IF(R137>0,P137-R137,"") | U137: =ROUND((E137-G137)*D137,0)
... A155: nan | D155: 0 | F155: =D155*E155 | H155: =IF(G155>0,ROUND(G155*1.19,0),"") | I155: =IF(H155>0,ROUND(H155*0.08,0),"") | J155: =IF(H155>0,H155+I155,"") | M155: =IF(AND(K155>0,J155>0),K155-J155,"") | N155: =IF(AND(L155>0,J155>0),L155-J155,"") | O155: =D155*K155 | P155: =D155*L155 | Q155: =IF(I155>0,I155*D155,"") | R155: =IF(J155>0,J155*D155,"") | S155: =IF(R155>0,O155-R155,"") | T155: =IF(R155>0,P155-R155,"") | U155: =ROUND((E155-G155)*D155,0)

Sheet Movimientos
A1: Fecha | B1: Hora | C1: Referencia | D1: Tipo | E1: Cantidad | F1: Stock anterior | G1: Stock nuevo | H1: Motivo | I1: Usuario
A2: 2026-06-08 | B2: 19:29 | C2: (TODAS) | D2: Compra | E2: 220 | F2: 0 | G2: 220 | H2: Carga inicial pedido 5 Junio | I2: sistema
A3: 2026-06-08 | B3: 19:31 | C3: KTR-4015 | D3: Venta | E3: -1 | F3: 2 | G3: 1 | H3: Prueba venta | I3: operador
A4: 2026-06-08 | B4: 19:31 | C4: KTR-4015 | D4: Sincronización | E4: -1 | F4: 2 | G4: 1 | H4: Ajuste detectado al sincronizar (cambio en Excel) | I4: sistema
A5: 2026-06-08 | B5: 19:36 | C5: KTR-4015 | D5: Venta | E5: -1 | F5: 1 | G5: 0 | H5: Prueba | I5: operador
A6: 2026-06-08 | B6: 19:43 | C6: KTR-4015 | D6: Entrada | E6: 2 | F6: 0 | G6: 2 | H6: Restaurar stock inicial | I6: operador

Sheet Guía producto nuevo
A1: Paso | B1: Instrucción
A2: 1. Cambiar stock | B2: Edita columna amarilla STOCK (piezas) en hoja Inventario.
A3: 2. Registrar movimiento | B3: Ejecuta: py -3 registrar_movimiento.py REF -1 "Venta taller"
A4: 3. Sincronizar PWA | B4: Ejecuta: py -3 sincronizar_inventario.py
A5: 4. Agregar producto nuevo | B5: En Inventario, busca fila ← NUEVO. Llena REFERENCIA, DESCRIPCIÓN, MARCA, STOCK, Catálogo y Facturado. Los precios Taller/Público se pueden calcular con el script o pegar manualmente.
A6: 5. Calcular precios auto | B6: py -3 inventario.py precios REFERENCIA — calcula taller/público desde catálogo.
A7: 6. Ocultar columnas grises | B7: Selecciona P–S → clic derecho → Ocultar.
A8: 7. Desbloquear edición | B8: Si Excel pide contraseña de hoja: apex
A9: 8. Plantilla vacía | B9: Usa Inventario_Apex_PLANTILLA.xlsx para empezar desde cero.
A10: 9. Pedido histórico | B10: Los análisis de pedidos van en carpeta pedidos/ — no mezclar con el VIVO.

Sheet Alertas
A1: Prioridad | B1: REFERENCIA | C1: DESCRIPCIÓN | D1: STOCK | E1: Acción sugerida
A2: STOCK BAJO | B2: KSA-CH043 | C2: Amortiguador Captiva 18-08 2.4 Del IZQ | D2: 1 | E2: Revisar / reponer pronto
A3: STOCK BAJO | B3: KSA-CH042 | C3: Amortiguador Captiva 18-08 2.4 Del DER | D3: 1 | E3: Revisar / reponer pronto
A4: STOCK BAJO | B4: KSA-DA001 | C4: Amortiguador Spark 7.24 / Daewoo Matiz II Del DER | D4: 1 | E4: Revisar / reponer pronto
A5: STOCK BAJO | B5: KSA-DA002 | C5: Amortiguador Spark 7.24 / Daewoo Matiz II Del IZQ | D5: 1 | E5: Revisar / reponer pronto
A6: STOCK BAJO | B6: KSA-FO001 | C6: Amortiguador Ford Fiesta Del IZQ | D6: 1 | E6: Revisar / reponer pronto
A7: STOCK BAJO | B7: KSA-FO002 | C7: Amortiguador Ford Fiesta Del DER | D7: 1 | E7: Revisar / reponer pronto
A8: STOCK BAJO | B8: KSA-HY014 | C8: Amortiguador Accent Vision / Kia Rio Xcite DEL DER | D8: 1 | E8: Revisar / reponer pronto
A9: STOCK BAJO | B9: KSA-HY015 | C9: Amortiguador Accent Vision / Kia Rio Xcite DEL IZQ | D9: 1 | E9: Revisar / reponer pronto
A10: STOCK BAJO | B10: KSA-KI024 | C10: Amortiguador Picanto ION Delantero Der GAS | D10: 1 | E10: Revisar / reponer pronto
A11: STOCK BAJO | B11: KSA-KI025 | C11: Amortiguador Kia Picanto 17-13 ION Del IZQ GAS | D11: 1 | E11: Revisar / reponer pronto
A12: STOCK BAJO | B12: KSA-MA001 | C12: Amortiguador Mazda 2 13-08 Del DER GAS | D12: 1 | E12: Revisar / reponer pronto
A13: STOCK BAJO | B13: KSA-MA002 | C13: Amortiguador Mazda 2 13-08 Del IZQ GAS | D13: 1 | E13: Revisar / reponer pronto
... A29: STOCK BAJO | B29: B32H-34-300 | C29: TIJERA DEL RH MAZDA 3 | D29: 1 | E29: Revisar / reponer pronto

Sheet Resumen
A1: Concepto | B1: Valor
A2: Total referencias activas | B2: =COUNTIF('Inventario'!A2:A155,"?*")
A3: Total piezas en stock | B3: =SUM('Inventario'!D2:D155)
A5: ── INVERSIÓN ──
A6: Inversión facturas con IVA (stock) | B6: =SUMPRODUCT('Inventario'!H2:H155,'Inventario'!D2:D155)
A7: Costo real total en bodega | B7: =SUM('Inventario'!R2:R155)
A8: Fondo logística moto (stock) | B8: =SUM('Inventario'!Q2:Q155)
A10: ── GANANCIA SI VENDES TODO EL STOCK ──
A11: Ganancia total Taller | B11: =SUM('Inventario'!S2:S155)
A12: Ganancia total Público | B12: =SUM('Inventario'!T2:T155)
A14: ── OTROS ──
A15: Ahorro mayorista (reinversión) | B15: =SUM('Inventario'!U2:U155)
A16: Última actualización precios | B16: 2026-06-22 19:02
