Workbook

Sheet Lista de Precios y Stock
A1: REFERENCIA | B1: DESCRIPCIÓN | C1: MARCA | D1: STOCK (piezas) | E1: Catálogo / pieza | F1: Total catálogo | G1: Facturado / pieza | H1: Total pagado factura (IVA) | I1: Precio Taller / pieza | J1: Precio Público / pieza | K1: Venta total Taller | L1: Venta total Público | M1: Costo real total | N1: Ganancia total Taller | O1: Ganancia total Público | P1: Ahorro mayorista total (reinversión) | Q1: Fondo logística total ($10k/pza) | R1: Ganancia neta Taller (sin domicilio) | S1: Ganancia neta Público (sin domicilio)
A2: KTR-4016 | B2: Terminal Dirección Optra DER | C2: Chevrolet | D2: 2 | E2: 27500 | F2: =D2*E2 | G2: 20625 | H2: =ROUND(D2*G2*1.19,0) | I2: 54776 | J2: 65731 | K2: =D2*I2 | L2: =D2*J2 | M2: =H2+Q2 | N2: =K2-M2 | O2: =L2-M2 | P2: =ROUND((E2-G2)*D2,0) | Q2: =D2*10000 | R2: =K2-H2 | S2: =L2-H2
A3: KSL-1005 | B3: Bieleta Estab. Luv Dmax 4x4 RT50 Del IZQ | C3: Chevrolet | D3: 2 | E3: 23630 | F3: =D3*E3 | G3: 17723 | H3: =ROUND(D3*G3*1.19,0) | I3: 48871 | J3: 58646 | K3: =D3*I3 | L3: =D3*J3 | M3: =H3+Q3 | N3: =K3-M3 | O3: =L3-M3 | P3: =ROUND((E3-G3)*D3,0) | Q3: =D3*10000 | R3: =K3-H3 | S3: =L3-H3
A4: KBJ-4013 | B4: Rótula Luv 2300 SUP | C4: Chevrolet | D4: 2 | E4: 31280 | F4: =D4*E4 | G4: 23460 | H4: =ROUND(D4*G4*1.19,0) | I4: 60543 | J4: 72651 | K4: =D4*I4 | L4: =D4*J4 | M4: =H4+Q4 | N4: =K4-M4 | O4: =L4-M4 | P4: =ROUND((E4-G4)*D4,0) | Q4: =D4*10000 | R4: =K4-H4 | S4: =L4-H4
A5: KTR-4035 | B5: Terminal Dirección Sail IZQ | C5: Chevrolet | D5: 2 | E5: 26580 | F5: =D5*E5 | G5: 19935 | H5: =ROUND(D5*G5*1.19,0) | I5: 53372 | J5: 64046 | K5: =D5*I5 | L5: =D5*J5 | M5: =H5+Q5 | N5: =K5-M5 | O5: =L5-M5 | P5: =ROUND((E5-G5)*D5,0) | Q5: =D5*10000 | R5: =K5-H5 | S5: =L5-H5
A6: KBJ-4001 | B6: Rótula Aveo-Sail | C6: Chevrolet | D6: 2 | E6: 23410 | F6: =D6*E6 | G6: 17558 | H6: =ROUND(D6*G6*1.19,0) | I6: 48536 | J6: 58243 | K6: =D6*I6 | L6: =D6*J6 | M6: =H6+Q6 | N6: =K6-M6 | O6: =L6-M6 | P6: =ROUND((E6-G6)*D6,0) | Q6: =D6*10000 | R6: =K6-H6 | S6: =L6-H6
A7: KTR-4034 | B7: Terminal Dirección Sail DER | C7: Chevrolet | D7: 2 | E7: 26580 | F7: =D7*E7 | G7: 19935 | H7: =ROUND(D7*G7*1.19,0) | I7: 53372 | J7: 64046 | K7: =D7*I7 | L7: =D7*J7 | M7: =H7+Q7 | N7: =K7-M7 | O7: =L7-M7 | P7: =ROUND((E7-G7)*D7,0) | Q7: =D7*10000 | R7: =K7-H7 | S7: =L7-H7
A8: KBJ-4008 | B8: Rótula Luv 2300 4x4 D-Max 4x2-4x4 Trooper INF (x2) | C8: Chevrolet | D8: 2 | E8: 47740 | F8: =D8*E8 | G8: 35805 | H8: =ROUND(D8*G8*1.19,0) | I8: 85655 | J8: 102786 | K8: =D8*I8 | L8: =D8*J8 | M8: =H8+Q8 | N8: =K8-M8 | O8: =L8-M8 | P8: =ROUND((E8-G8)*D8,0) | Q8: =D8*10000 | R8: =K8-H8 | S8: =L8-H8
A9: KTR-4019 | B9: Terminal Dir Spark GT 1.2 | C9: Chevrolet | D9: 2 | E9: 27680 | F9: =D9*E9 | G9: 20760 | H9: =ROUND(D9*G9*1.19,0) | I9: 55050 | J9: 66060 | K9: =D9*I9 | L9: =D9*J9 | M9: =H9+Q9 | N9: =K9-M9 | O9: =L9-M9 | P9: =ROUND((E9-G9)*D9,0) | Q9: =D9*10000 | R9: =K9-H9 | S9: =L9-H9
A10: KTR-4015 | B10: Terminal Dir Optra IZQ | C10: Chevrolet | D10: 2 | E10: 27500 | F10: =D10*E10 | G10: 20625 | H10: =ROUND(D10*G10*1.19,0) | I10: 54776 | J10: 65731 | K10: =D10*I10 | L10: =D10*J10 | M10: =H10+Q10 | N10: =K10-M10 | O10: =L10-M10 | P10: =ROUND((E10-G10)*D10,0) | Q10: =D10*10000 | R10: =K10-H10 | S10: =L10-H10
A11: KTR-4002 | B11: Terminal Dir Aveo DER | C11: Chevrolet | D11: 2 | E11: 24820 | F11: =D11*E11 | G11: 18615 | H11: =ROUND(D11*G11*1.19,0) | I11: 50687 | J11: 60824 | K11: =D11*I11 | L11: =D11*J11 | M11: =H11+Q11 | N11: =K11-M11 | O11: =L11-M11 | P11: =ROUND((E11-G11)*D11,0) | Q11: =D11*10000 | R11: =K11-H11 | S11: =L11-H11
A12: KTR-4003 | B12: Terminal Dir Aveo IZQ | C12: Chevrolet | D12: 2 | E12: 24820 | F12: =D12*E12 | G12: 18615 | H12: =ROUND(D12*G12*1.19,0) | I12: 50687 | J12: 60824 | K12: =D12*I12 | L12: =D12*J12 | M12: =H12+Q12 | N12: =K12-M12 | O12: =L12-M12 | P12: =ROUND((E12-G12)*D12,0) | Q12: =D12*10000 | R12: =K12-H12 | S12: =L12-H12
A13: KSL-1006 | B13: Bieleta Estab. Luv D-Max 4x4 RT-50 Del DER | C13: Chevrolet | D13: 2 | E13: 23630 | F13: =D13*E13 | G13: 17723 | H13: =ROUND(D13*G13*1.19,0) | I13: 48871 | J13: 58646 | K13: =D13*I13 | L13: =D13*J13 | M13: =H13+Q13 | N13: =K13-M13 | O13: =L13-M13 | P13: =ROUND((E13-G13)*D13,0) | Q13: =D13*10000 | R13: =K13-H13 | S13: =L13-H13
... A125: B32H-34-300 | B125: TIJERA DEL RH MAZDA 3 | C125: Mazda | D125: 1 | E125: 100840 | F125: =D125*E125 | G125: 90756 | H125: =ROUND(D125*G125*1.19,0) | I125: 166667 | J125: 200000 | K125: =D125*I125 | L125: =D125*J125 | M125: =H125+Q125 | N125: =K125-M125 | O125: =L125-M125 | P125: =ROUND((E125-G125)*D125,0) | Q125: =D125*10000 | R125: =K125-H125 | S125: =L125-H125

Sheet Resumen
A1: Concepto | B1: Valor
A2: Total referencias | B2: =COUNTA('Lista de Precios y Stock'!A2:A125)
A3: Total piezas en stock | B3: =SUM('Lista de Precios y Stock'!D2:D125)
A4: Valor catálogo total | B4: =SUM('Lista de Precios y Stock'!F2:F125)
A5: Total pagado en facturas (IVA) | B5: =SUM('Lista de Precios y Stock'!H2:H125)
A6: Proyección venta total Taller | B6: =SUM('Lista de Precios y Stock'!K2:K125)
A7: Proyección venta total Público | B7: =SUM('Lista de Precios y Stock'!L2:L125)
A8: Costo real total del stock | B8: =SUM('Lista de Precios y Stock'!M2:M125)
A9: Ganancia si vende todo a Taller | B9: =SUM('Lista de Precios y Stock'!N2:N125)
A10: Ganancia si vende todo a Público | B10: =SUM('Lista de Precios y Stock'!O2:O125)
A11: Total ahorro mayorista (reinversión) | B11: =SUM('Lista de Precios y Stock'!P2:P125)
A12: Total fondo logística domicilios | B12: =SUM('Lista de Precios y Stock'!Q2:Q125)
A13: Ganancia neta Taller (sin domicilio) | B13: =SUM('Lista de Precios y Stock'!R2:R125)
A14: Ganancia neta Público (sin domicilio) | B14: =SUM('Lista de Precios y Stock'!S2:S125)

Sheet Notas
A1: Regla | B1: Descripción
A2: STOCK (piezas) | B2: Columna amarilla. Cámbiala al hacer inventario (3, 5, 0…). Todo se recalcula solo.
A3: Catálogo / pieza | B3: Precio de lista del proveedor. Base para cobrar (NO incluye descuento mayorista).
A4: Total catálogo | B4: Fórmula: STOCK × Catálogo / pieza
A5: Facturado / pieza | B5: Lo que pagaste realmente (mayorista). Solo para tu control interno.
A6: Precios Taller / Público | B6: Calculados con catálogo + IVA + $10.000 oculto. Margen 22% y 35%.
A7: Costo real total (col M) | B7: Fórmula: H + Q. Lo pagado al proveedor con IVA + provisión domicilio ($10k × stock).
A8: Ganancia Taller/Público (col N/O) | B8: Venta total − Costo real (M). Ya separa los $10k/pza para logística.
A9: Columnas P–S (gris) | B9: Ocultar con clic derecho > Ocultar. Análisis interno y reinversión.
A10: Ahorro mayorista (col P) | B10: Fórmula: (Catálogo − Facturado) × STOCK, sin IVA.
A11: Fondo logística (col Q) | B11: Fórmula: STOCK × $10.000. Provisión domicilios; va aparte de la ganancia del repuesto.
A12: Ganancia neta sin domicilio (col R/S) | B12: Fórmula: Venta total − Total pagado factura (H). Utilidad limpia del repuesto, sin descontar provisión logística.
... A14: PWA | B14: Subir carga-pwa-catalogo.json. Descuento taller recomendado: 16.67%.
